xllm/__init__.py
xllm/__main__.py
xllm/enums.py
xllm/types.py
xllm/cli/__init__.py
xllm/cli/download.py
xllm/cli/fuse.py
xllm/cli/gptq_quantize.py
xllm/cli/quantize.py
xllm/cli/train.py
xllm/collators/__init__.py
xllm/collators/base.py
xllm/collators/completion.py
xllm/collators/lm.py
xllm/collators/registry.py
xllm/core/__init__.py
xllm/core/config.py
xllm/core/constants.py
xllm/core/deepspeed_configs.py
xllm/core/dependencies.py
xllm/datasets/__init__.py
xllm/datasets/base.py
xllm/datasets/general.py
xllm/datasets/registry.py
xllm/datasets/soda.py
xllm/experiments/__init__.py
xllm/experiments/base.py
xllm/experiments/registry.py
xllm/quantization/__init__.py
xllm/quantization/quantizer.py
xllm/run/__init__.py
xllm/run/download.py
xllm/run/fuse.py
xllm/run/gptq_quantize.py
xllm/run/quantize.py
xllm/run/train.py
xllm/trainers/__init__.py
xllm/trainers/lm.py
xllm/trainers/registry.py
xllm/utils/__init__.py
xllm/utils/cli.py
xllm/utils/logger.py
xllm/utils/miscellaneous.py
xllm/utils/nn.py
xllm/utils/post_training.py
xllm/utils/registry.py
xllm-0.3.24.dist-info/LICENSE
xllm-0.3.24.dist-info/METADATA
xllm-0.3.24.dist-info/WHEEL
xllm-0.3.24.dist-info/top_level.txt
xllm-0.3.24.dist-info/RECORD
