Metadata-Version: 2.1
Name: xllm
Version: 0.3.24
Summary: Simple & Cutting Edge LLM Finetuning
Home-page: https://github.com/kompleteai/xllm
Author: BobaZooba
Author-email: bobazooba@gmail.com
License: Apache
Keywords: ai nlp llm text deep-learning
Platform: UNKNOWN
Classifier: Development Status :: 5 - Production/Stable
Classifier: Intended Audience :: Developers
Classifier: Intended Audience :: Education
Classifier: Intended Audience :: Science/Research
Classifier: License :: OSI Approved :: Apache Software License
Classifier: Operating System :: OS Independent
Classifier: Programming Language :: Python :: 3
Classifier: Programming Language :: Python :: 3.8
Classifier: Topic :: Scientific/Engineering :: Artificial Intelligence
Requires-Python: >=3.8
Requires-Dist: numpy >=1.17
Requires-Dist: packaging >=20.0
Requires-Dist: psutil
Requires-Dist: torch >=2.0.1
Requires-Dist: loguru
Requires-Dist: peft >=0.5.0
Requires-Dist: wandb
Requires-Dist: python-dotenv
Requires-Dist: requests
Requires-Dist: optimum >=1.12.0
Requires-Dist: bitsandbytes >=0.41.1
Requires-Dist: scipy
Requires-Dist: transformers
Requires-Dist: tqdm
Requires-Dist: safetensors
Provides-Extra: all
Requires-Dist: deepspeed ; extra == 'all'
Requires-Dist: flash-attn >=2.2.1 ; extra == 'all'
Requires-Dist: auto-gptq ; extra == 'all'
Requires-Dist: black ; extra == 'all'
Requires-Dist: mypy ; extra == 'all'
Requires-Dist: mypy-extensions ; extra == 'all'
Requires-Dist: pre-commit ; extra == 'all'
Requires-Dist: ruff ; extra == 'all'
Requires-Dist: pytest ; extra == 'all'
Requires-Dist: coverage ; extra == 'all'
Requires-Dist: pytest-html ; extra == 'all'
Requires-Dist: pytest-cov ; extra == 'all'
Requires-Dist: wheel ; extra == 'all'
Requires-Dist: twine ; extra == 'all'
Provides-Extra: auto-gptq
Requires-Dist: auto-gptq ; extra == 'auto-gptq'
Provides-Extra: build
Requires-Dist: wheel ; extra == 'build'
Requires-Dist: twine ; extra == 'build'
Provides-Extra: deepspeed
Requires-Dist: deepspeed ; extra == 'deepspeed'
Provides-Extra: dev
Requires-Dist: black ; extra == 'dev'
Requires-Dist: mypy ; extra == 'dev'
Requires-Dist: mypy-extensions ; extra == 'dev'
Requires-Dist: pre-commit ; extra == 'dev'
Requires-Dist: ruff ; extra == 'dev'
Requires-Dist: pytest ; extra == 'dev'
Requires-Dist: coverage ; extra == 'dev'
Requires-Dist: pytest-html ; extra == 'dev'
Requires-Dist: pytest-cov ; extra == 'dev'
Requires-Dist: wheel ; extra == 'dev'
Requires-Dist: twine ; extra == 'dev'
Provides-Extra: flash-attn
Requires-Dist: flash-attn >=2.2.1 ; extra == 'flash-attn'
Provides-Extra: quality
Requires-Dist: black ; extra == 'quality'
Requires-Dist: mypy ; extra == 'quality'
Requires-Dist: mypy-extensions ; extra == 'quality'
Requires-Dist: pre-commit ; extra == 'quality'
Requires-Dist: ruff ; extra == 'quality'
Provides-Extra: tests
Requires-Dist: pytest ; extra == 'tests'
Requires-Dist: coverage ; extra == 'tests'
Requires-Dist: pytest-html ; extra == 'tests'
Requires-Dist: pytest-cov ; extra == 'tests'
Provides-Extra: train
Requires-Dist: deepspeed ; extra == 'train'
Requires-Dist: flash-attn >=2.2.1 ; extra == 'train'
Requires-Dist: auto-gptq ; extra == 'train'
